odoo/addons/mail_restrict_send_button/README.rst
odoo/addons/mail_restrict_send_button/__init__.py
odoo/addons/mail_restrict_send_button/__manifest__.py
odoo/addons/mail_restrict_send_button/i18n/it.po
odoo/addons/mail_restrict_send_button/i18n/mail_restrict_send_button.pot
odoo/addons/mail_restrict_send_button/readme/CONFIGURE.rst
odoo/addons/mail_restrict_send_button/readme/CONTRIBUTORS.rst
odoo/addons/mail_restrict_send_button/readme/DESCRIPTION.rst
odoo/addons/mail_restrict_send_button/security/res_groups.xml
odoo/addons/mail_restrict_send_button/static/description/icon.png
odoo/addons/mail_restrict_send_button/static/description/index.html
odoo/addons/mail_restrict_send_button/static/src/js/chatter.esm.js
odoo/addons/mail_restrict_send_button/static/src/xml/chatter.xml
odoo_addon_mail_restrict_send_button-16.0.1.0.1.5.dist-info/METADATA
odoo_addon_mail_restrict_send_button-16.0.1.0.1.5.dist-info/WHEEL
odoo_addon_mail_restrict_send_button-16.0.1.0.1.5.dist-info/top_level.txt
odoo_addon_mail_restrict_send_button-16.0.1.0.1.5.dist-info/RECORD
